Metadata-Version: 1.1
Name: nelxte
Version: 1.1
Summary: Nelxte is a fast and open source python library for checking password strength.
Home-page: UNKNOWN
Author: Amay Agarwal
Author-email: UNKNOWN
License: MIT
Download-URL: https://github.com/amay428/nelxte_lib/archive/1.1.tar.gz
Platform: UNKNOWN
